Metadata-Version: 2.4
Name: adafruit-circuitpython-sgp30
Version: 3.0.14
Summary: CircuitPython library for Sensirion SGP30 gas sensor with eCO2 and TVOC.
Author-email: Adafruit Industries <circuitpython@adafruit.com>
License: MIT
Project-URL: Homepage, https://github.com/adafruit/Adafruit_CircuitPython_SGP30
Keywords: adafruit,sensiron,sgp30,gas,sensor,eco2,tvoc,h2,ethanol,i2c,hardware,micropython,circuitpython
Classifier: Intended Audience :: Developers
Classifier: Topic :: Software Development :: Libraries
Classifier: Topic :: Software Development :: Embedded Systems
Classifier: Topic :: System :: Hardware
Classifier: License :: OSI Approved :: MIT License
Classifier: Programming Language :: Python :: 3
License-File: LICENSE
Requires-Dist: Adafruit-Blinka
Requires-Dist: adafruit-circuitpython-busdevice
Provides-Extra: optional
Dynamic: license-file
